webgeodyn/.gitattributes
webgeodyn/__init__.py
webgeodyn/_version.py
webgeodyn/constants.py
webgeodyn/example.py
webgeodyn/data/GHData.py
webgeodyn/data/TSData.py
webgeodyn/data/__init__.py
webgeodyn/data/measuredata.py
webgeodyn/data/normPnm.py
webgeodyn/filters/__init__.py
webgeodyn/filters/spectral.py
webgeodyn/filters/time.py
webgeodyn/inout/__init__.py
webgeodyn/inout/archeomag.py
webgeodyn/inout/ced.py
webgeodyn/inout/ced746.py
webgeodyn/inout/chaos.py
webgeodyn/inout/coreflo-ll.py
webgeodyn/inout/covobs.py
webgeodyn/inout/covobs_splines.py
webgeodyn/inout/covobs_x2.py
webgeodyn/inout/default.py
webgeodyn/inout/enscore.py
webgeodyn/inout/lod.py
webgeodyn/inout/midpath.py
webgeodyn/inout/nath.py
webgeodyn/inout/pygeodyn_asc.py
webgeodyn/inout/pygeodyn_hdf5.py
webgeodyn/inout/pygeodyn_hdf5_forecasts.py
webgeodyn/inout/s1fs.py
webgeodyn/inout/s1fs2.py
webgeodyn/inout/zforecast.py
webgeodyn/models/__init__.py
webgeodyn/models/model.py
webgeodyn/models/models.py
webgeodyn/obsdata/__init__.py
webgeodyn/obsdata/obsdata.py
webgeodyn/obsdata/observatory.py
webgeodyn/obsdata/GO-VO_cdf/GO_data/GO_data/GObs_12M_19970701T000000_20230701T000000_0108.cdf
webgeodyn/obsdata/GO-VO_cdf/GO_data/GO_data/GObs_4M_19970301T000000_20231101T000000_0108.cdf
webgeodyn/obsdata/GO-VO_cdf/GO_data/GO_data/ReadMe_GO.txt
webgeodyn/obsdata/GO-VO_cdf/GVO_data_CHAMP/GVO_data_CHAMP/.DS_Store
webgeodyn/obsdata/GO-VO_cdf/GVO_data_CHAMP/GVO_data_CHAMP/CH_OPER_VOBS_12M_2__20000701T000000_20100701T000000_0201.cdf
webgeodyn/obsdata/GO-VO_cdf/GVO_data_CHAMP/GVO_data_CHAMP/CH_OPER_VOBS_4M_2__20000701T000000_20100701T000000_0201.cdf
webgeodyn/obsdata/GO-VO_cdf/GVO_data_CHAMP/GVO_data_CHAMP/ReadMe.txt
webgeodyn/obsdata/GO-VO_cdf/GVO_data_CRYOSAT2/GVO_data_CRYOSAT2/.DS_Store
webgeodyn/obsdata/GO-VO_cdf/GVO_data_CRYOSAT2/GVO_data_CRYOSAT2/CR_OPER_VOBS_12M_2__20100701T000000_20180701T000000_0201.cdf
webgeodyn-0.10.5.dist-info/AUTHORS.txt
webgeodyn-0.10.5.dist-info/LICENSE.txt
webgeodyn-0.10.5.dist-info/METADATA
webgeodyn-0.10.5.dist-info/WHEEL
webgeodyn-0.10.5.dist-info/top_level.txt
webgeodyn-0.10.5.dist-info/RECORD
