Metadata-Version: 2.1
Name: webgeodyn
Version: 0.10.5
Summary: A web-based plot tool to visualize Earth core flows
Home-page: https://gricad-gitlab.univ-grenoble-alpes.fr/Geodynamo/webgeodyn
Author: Nicolas Gillet, Loïc Huder, Yannick Martin, Franck Thollard, Mathieu Istas, François Dallasta, 
Author-email: francois.dall-asta@univ-grenoble-alpes.fr
License: UNKNOWN
Platform: UNKNOWN
Classifier: Programming Language :: Python :: 3 :: Only
Classifier: Programming Language :: Python :: 3.5
Classifier: Programming Language :: Python :: 3.6
Classifier: Programming Language :: Python :: 3.7
Classifier: Programming Language :: Python :: 3.8
Classifier: Programming Language :: Python :: 3.9
Classifier: Programming Language :: Python :: 3.10
Classifier: Programming Language :: JavaScript
Classifier: License :: OSI Approved :: GNU General Public License v3 (GPLv3)
Classifier: Intended Audience :: Science/Research
Classifier: Intended Audience :: Education
Classifier: Topic :: Scientific/Engineering :: Physics
Classifier: Topic :: Scientific/Engineering :: Visualization
License-File: LICENSE.txt
License-File: AUTHORS.txt
Requires-Dist: astropy
Requires-Dist: cdflib
Requires-Dist: h5py
Requires-Dist: numpy
Requires-Dist: scipy (>1.1)
Requires-Dist: tornado
